NOTICE
superlinked/server/__main__.py
superlinked/server/app.py
superlinked/server/configuration/settings.py
superlinked/server/dependency_register.py
superlinked/server/exception/__init__.py
superlinked/server/exception/exception.py
superlinked/server/exception/exception_handler.py
superlinked/server/logger.py
superlinked/server/middleware/__init__.py
superlinked/server/middleware/api_key_auth.py
superlinked/server/middleware/lifespan_event.py
superlinked/server/middleware/timing_middleware.py
superlinked/server/openapi/ingest_endpoint_descriptor.json
superlinked/server/openapi/query_endpoint_descriptor.json
superlinked/server/py.typed
superlinked/server/router/__init__.py
superlinked/server/router/management_router.py
superlinked/server/service/__init__.py
superlinked/server/service/data_loader.py
superlinked/server/service/file_handler_service.py
superlinked/server/service/file_object_serializer.py
superlinked/server/service/persistence_service.py
superlinked/server/util/__init__.py
superlinked/server/util/fast_api_handler.py
superlinked/server/util/open_api_schema_generator.py
superlinked/server/util/superlinked_app_downloader_util.py
superlinked_server-1.56.4.dist-info/LICENSE
superlinked_server-1.56.4.dist-info/METADATA
superlinked_server-1.56.4.dist-info/NOTICE
superlinked_server-1.56.4.dist-info/WHEEL
superlinked_server-1.56.4.dist-info/RECORD
