Metadata-Version: 2.1
Name: superlinked-server
Version: 1.56.4
Summary: Superlinked server enables fast and scalable vector search and storage
License: Apache-2.0
Author: Superlinked Release
Author-email: release@superlinked.com
Requires-Python: >=3.10.3,<=3.12.3
Classifier: License :: OSI Approved :: Apache Software License
Classifier: Programming Language :: Python :: 3
Classifier: Programming Language :: Python :: 3.11
Classifier: Programming Language :: Python :: 3.12
Requires-Dist: asgi-correlation-id (>=4.3.3,<5.0.0)
Requires-Dist: fastapi (>=0.115,<0.117)
Requires-Dist: fastapi-restful (>=0.6.0,<0.7.0)
Requires-Dist: fastparquet (>=2024.11.0,<2025.0.0)
Requires-Dist: fsspec (>=2024.10.0,<2025.0.0)
Requires-Dist: gcsfs (>=2024.10.0,<2025.0.0)
Requires-Dist: inject (>=5.2.0,<6.0.0)
Requires-Dist: opentelemetry-exporter-otlp-proto-grpc (>=1.36.0,<2.0.0)
Requires-Dist: orjson (>=3.11.3,<4.0.0)
Requires-Dist: pandas (>=2.0.3,<3.0.0)
Requires-Dist: pydantic (>=2.6.3,<3.0.0)
Requires-Dist: pydantic-settings (>=2.5.2,<3.0.0)
Requires-Dist: python-json-logger (>=2.0.7,<4.0.0)
Requires-Dist: s3fs (>=2024.10.0,<2025.0.0)
Requires-Dist: sentry-sdk[fastapi] (>=2.24.1,<3.0.0)
Requires-Dist: structlog-sentry (>=2.2.1,<3.0.0)
Requires-Dist: superlinked[mongo,pub-sub,qdrant,redis,storage] (>=37.4.2,<38.0.0)
Requires-Dist: typing-inspect (>=0.9.0,<0.10.0)
Requires-Dist: uvicorn (>=0.32,<0.36)
